pandahelper/__init__.py
pandahelper/profiles.py
pandahelper/stats.py
pandahelper/times.py
panda_helper-0.1.2.dist-info/LICENSE
panda_helper-0.1.2.dist-info/METADATA
panda_helper-0.1.2.dist-info/WHEEL
panda_helper-0.1.2.dist-info/top_level.txt
panda_helper-0.1.2.dist-info/RECORD
