Metadata-Version: 2.2
Name: panda-helper
Version: 0.1.2
Summary: Data profiler for Pandas
Author-email: Ray310 <ray310@pm.me>
License: MIT License
Project-URL: Homepage, https://ray310.github.io/Panda-Helper/
Project-URL: Repository, https://github.com/ray310/Panda-Helper
Project-URL: Issues, https://github.com/ray310/Panda-Helper/issues
Keywords: data-profiling,data-profiling-utility,data-analysis
Classifier: Development Status :: 4 - Beta
Classifier: Programming Language :: Python :: 3.9
Classifier: Programming Language :: Python :: 3.10
Classifier: Programming Language :: Python :: 3.11
Classifier: Programming Language :: Python :: 3.12
Classifier: Programming Language :: Python :: 3.13
Classifier: Operating System :: OS Independent
Classifier: Topic :: Software Development
Classifier: Topic :: Scientific/Engineering
Classifier: Topic :: Scientific/Engineering :: Information Analysis
Requires-Python: >=3.9
License-File: LICENSE
Requires-Dist: beautifulsoup4>=4.12.2
Requires-Dist: numpy>=1.26.0
Requires-Dist: pandas>=2.1.1
Requires-Dist: scipy>=1.11.2
Requires-Dist: tabulate==0.9.0
Provides-Extra: test
Requires-Dist: pytest>=7.4; extra == "test"
Requires-Dist: pylint>=3.0; extra == "test"
